<?xml version="1.0" encoding="utf-8"?>
<openerp>
	<data>
		<record model="ir.ui.view" id="qunar_balance_ledger_filter_partner_form">
			<field name="name">qunar.balance.ledger.filter.partner.form</field>
			<field name="model">account.partner.ledger</field>
			<field name="inherit_id" ref="account.account_common_report_view"/>
			<field name="arch" type="xml">
				<field name="chart_account_id" position="after">
		  			<field name="partner_id"/>
				</field>
			</field>
		</record>
	</data>
</openerp>
